aiohttp_fast_zlib/__init__.py
aiohttp_fast_zlib/py.typed
aiohttp_fast_zlib-0.2.3.dist-info/LICENSE
aiohttp_fast_zlib-0.2.3.dist-info/METADATA
aiohttp_fast_zlib-0.2.3.dist-info/WHEEL
aiohttp_fast_zlib-0.2.3.dist-info/RECORD
