Metadata-Version: 2.3
Name: aiohttp-fast-zlib
Version: 0.2.3
Summary: Use the fastest installed zlib compatible library with aiohttp
License: Apache-2.0
Author: J. Nick Koston
Author-email: nick@koston.org
Requires-Python: >=3.9
Classifier: Development Status :: 2 - Pre-Alpha
Classifier: Intended Audience :: Developers
Classifier: License :: OSI Approved :: Apache Software License
Classifier: Natural Language :: English
Classifier: Operating System :: OS Independent
Classifier: Programming Language :: Python :: 3
Classifier: Programming Language :: Python :: 3.9
Classifier: Programming Language :: Python :: 3.10
Classifier: Programming Language :: Python :: 3.11
Classifier: Programming Language :: Python :: 3.12
Classifier: Programming Language :: Python :: 3.13
Classifier: Topic :: Software Development :: Libraries
Provides-Extra: isal
Provides-Extra: zlib-ng
Requires-Dist: aiohttp (>=3.9.0)
Requires-Dist: isal (>=1.6.1) ; extra == "isal"
Requires-Dist: zlib_ng (>=0.4.3) ; extra == "zlib-ng"
Project-URL: Bug Tracker, https://github.com/bluetooth-devices/aiohttp-fast-zlib/issues
Project-URL: Changelog, https://github.com/bluetooth-devices/aiohttp-fast-zlib/blob/main/CHANGELOG.md
Project-URL: Repository, https://github.com/bluetooth-devices/aiohttp-fast-zlib
